responder/__init__.py
responder/__main__.py
responder/__version__.py
responder/api.py
responder/background.py
responder/cli.py
responder/core.py
responder/formats.py
responder/models.py
responder/routes.py
responder/staticfiles.py
responder/statics.py
responder/status_codes.py
responder/templates.py
responder/ext/__init__.py
responder/ext/graphql/__init__.py
responder/ext/graphql/templates.py
responder/ext/schema/__init__.py
responder-2.0.7.dist-info/LICENSE
responder-2.0.7.dist-info/METADATA
responder-2.0.7.dist-info/WHEEL
responder-2.0.7.dist-info/entry_points.txt
responder-2.0.7.dist-info/top_level.txt
responder-2.0.7.dist-info/RECORD
