Metadata-Version: 2.1
Name: responder
Version: 2.0.7
Summary: A sorta familiar HTTP framework.
Home-page: https://github.com/kennethreitz/responder
Author: Kenneth Reitz
Author-email: me@kennethreitz.org
License: Apache 2.0
Platform: UNKNOWN
Classifier: License :: OSI Approved :: Apache Software License
Classifier: Programming Language :: Python
Classifier: Programming Language :: Python :: 3
Classifier: Programming Language :: Python :: 3.6
Classifier: Programming Language :: Python :: 3.7
Classifier: Programming Language :: Python :: Implementation :: CPython
Classifier: Programming Language :: Python :: Implementation :: PyPy
Requires-Python: >=3.6
